pr_review_bot/__init__.py
pr_review_bot-0.2.1.dist-info/LICENSE
pr_review_bot-0.2.1.dist-info/METADATA
pr_review_bot-0.2.1.dist-info/WHEEL
pr_review_bot-0.2.1.dist-info/entry_points.txt
pr_review_bot-0.2.1.dist-info/top_level.txt
pr_review_bot-0.2.1.dist-info/RECORD
