Metadata-Version: 2.1
Name: pr-review-bot
Version: 0.2.1
Summary: Automated PR review bot using GPT-3.5-turbo
Author-email: Kyryl Truskovskyi <truskovskiyk@gmail.com>
License: Apache License
License-File: LICENSE
